{"nodes": [{"id": "c_users_salivs_data_laragon_www_drent_vibe_backend_vendor_phpunit_php_code_coverage_changelog_12_5_md", "label": "ChangeLog-12.5.md", "file_type": "document", "source_file": "C:\\Users\\Salivs\\Data\\laragon\\www\\drent-vibe\\backend\\vendor\\phpunit\\php-code-coverage\\ChangeLog-12.5.md", "source_location": "L1"}, {"id": "php_code_coverage_changelog_12_5_changelog", "label": "ChangeLog", "file_type": "document", "source_file": "C:\\Users\\Salivs\\Data\\laragon\\www\\drent-vibe\\backend\\vendor\\phpunit\\php-code-coverage\\ChangeLog-12.5.md", "source_location": "L1"}, {"id": "php_code_coverage_changelog_12_5_12_5_6_2026_04_15", "label": "[12.5.6] - 2026-04-15", "file_type": "document", "source_file": "C:\\Users\\Salivs\\Data\\laragon\\www\\drent-vibe\\backend\\vendor\\phpunit\\php-code-coverage\\ChangeLog-12.5.md", "source_location": "L5"}, {"id": "php_code_coverage_changelog_12_5_fixed", "label": "Fixed", "file_type": "document", "source_file": "C:\\Users\\Salivs\\Data\\laragon\\www\\drent-vibe\\backend\\vendor\\phpunit\\php-code-coverage\\ChangeLog-12.5.md", "source_location": "L7"}, {"id": "php_code_coverage_changelog_12_5_12_5_5_2026_04_13", "label": "[12.5.5] - 2026-04-13", "file_type": "document", "source_file": "C:\\Users\\Salivs\\Data\\laragon\\www\\drent-vibe\\backend\\vendor\\phpunit\\php-code-coverage\\ChangeLog-12.5.md", "source_location": "L11"}, {"id": "php_code_coverage_changelog_12_5_fixed_13", "label": "Fixed", "file_type": "document", "source_file": "C:\\Users\\Salivs\\Data\\laragon\\www\\drent-vibe\\backend\\vendor\\phpunit\\php-code-coverage\\ChangeLog-12.5.md", "source_location": "L13"}, {"id": "php_code_coverage_changelog_12_5_12_5_4_2026_04_12", "label": "[12.5.4] - 2026-04-12", "file_type": "document", "source_file": "C:\\Users\\Salivs\\Data\\laragon\\www\\drent-vibe\\backend\\vendor\\phpunit\\php-code-coverage\\ChangeLog-12.5.md", "source_location": "L17"}, {"id": "php_code_coverage_changelog_12_5_fixed_19", "label": "Fixed", "file_type": "document", "source_file": "C:\\Users\\Salivs\\Data\\laragon\\www\\drent-vibe\\backend\\vendor\\phpunit\\php-code-coverage\\ChangeLog-12.5.md", "source_location": "L19"}, {"id": "php_code_coverage_changelog_12_5_12_5_3_2026_02_06", "label": "[12.5.3] - 2026-02-06", "file_type": "document", "source_file": "C:\\Users\\Salivs\\Data\\laragon\\www\\drent-vibe\\backend\\vendor\\phpunit\\php-code-coverage\\ChangeLog-12.5.md", "source_location": "L23"}, {"id": "php_code_coverage_changelog_12_5_fixed_25", "label": "Fixed", "file_type": "document", "source_file": "C:\\Users\\Salivs\\Data\\laragon\\www\\drent-vibe\\backend\\vendor\\phpunit\\php-code-coverage\\ChangeLog-12.5.md", "source_location": "L25"}, {"id": "php_code_coverage_changelog_12_5_12_5_2_2025_12_24", "label": "[12.5.2] - 2025-12-24", "file_type": "document", "source_file": "C:\\Users\\Salivs\\Data\\laragon\\www\\drent-vibe\\backend\\vendor\\phpunit\\php-code-coverage\\ChangeLog-12.5.md", "source_location": "L29"}, {"id": "php_code_coverage_changelog_12_5_fixed_31", "label": "Fixed", "file_type": "document", "source_file": "C:\\Users\\Salivs\\Data\\laragon\\www\\drent-vibe\\backend\\vendor\\phpunit\\php-code-coverage\\ChangeLog-12.5.md", "source_location": "L31"}, {"id": "php_code_coverage_changelog_12_5_12_5_1_2025_12_08", "label": "[12.5.1] - 2025-12-08", "file_type": "document", "source_file": "C:\\Users\\Salivs\\Data\\laragon\\www\\drent-vibe\\backend\\vendor\\phpunit\\php-code-coverage\\ChangeLog-12.5.md", "source_location": "L35"}, {"id": "php_code_coverage_changelog_12_5_changed", "label": "Changed", "file_type": "document", "source_file": "C:\\Users\\Salivs\\Data\\laragon\\www\\drent-vibe\\backend\\vendor\\phpunit\\php-code-coverage\\ChangeLog-12.5.md", "source_location": "L37"}, {"id": "php_code_coverage_changelog_12_5_12_5_0_2025_11_29", "label": "[12.5.0] - 2025-11-29", "file_type": "document", "source_file": "C:\\Users\\Salivs\\Data\\laragon\\www\\drent-vibe\\backend\\vendor\\phpunit\\php-code-coverage\\ChangeLog-12.5.md", "source_location": "L41"}, {"id": "php_code_coverage_changelog_12_5_added", "label": "Added", "file_type": "document", "source_file": "C:\\Users\\Salivs\\Data\\laragon\\www\\drent-vibe\\backend\\vendor\\phpunit\\php-code-coverage\\ChangeLog-12.5.md", "source_location": "L43"}, {"id": "php_code_coverage_changelog_12_5_changed_47", "label": "Changed", "file_type": "document", "source_file": "C:\\Users\\Salivs\\Data\\laragon\\www\\drent-vibe\\backend\\vendor\\phpunit\\php-code-coverage\\ChangeLog-12.5.md", "source_location": "L47"}], "edges": [{"source": "c_users_salivs_data_laragon_www_drent_vibe_backend_vendor_phpunit_php_code_coverage_changelog_12_5_md", "target": "php_code_coverage_changelog_12_5_changelog", "relation": "contains", "confidence": "EXTRACTED", "source_file": "C:\\Users\\Salivs\\Data\\laragon\\www\\drent-vibe\\backend\\vendor\\phpunit\\php-code-coverage\\ChangeLog-12.5.md", "source_location": "L1", "weight": 1.0}, {"source": "php_code_coverage_changelog_12_5_changelog", "target": "php_code_coverage_changelog_12_5_12_5_6_2026_04_15", "relation": "contains", "confidence": "EXTRACTED", "source_file": "C:\\Users\\Salivs\\Data\\laragon\\www\\drent-vibe\\backend\\vendor\\phpunit\\php-code-coverage\\ChangeLog-12.5.md", "source_location": "L5", "weight": 1.0}, {"source": "php_code_coverage_changelog_12_5_12_5_6_2026_04_15", "target": "php_code_coverage_changelog_12_5_fixed", "relation": "contains", "confidence": "EXTRACTED", "source_file": "C:\\Users\\Salivs\\Data\\laragon\\www\\drent-vibe\\backend\\vendor\\phpunit\\php-code-coverage\\ChangeLog-12.5.md", "source_location": "L7", "weight": 1.0}, {"source": "php_code_coverage_changelog_12_5_changelog", "target": "php_code_coverage_changelog_12_5_12_5_5_2026_04_13", "relation": "contains", "confidence": "EXTRACTED", "source_file": "C:\\Users\\Salivs\\Data\\laragon\\www\\drent-vibe\\backend\\vendor\\phpunit\\php-code-coverage\\ChangeLog-12.5.md", "source_location": "L11", "weight": 1.0}, {"source": "php_code_coverage_changelog_12_5_12_5_5_2026_04_13", "target": "php_code_coverage_changelog_12_5_fixed_13", "relation": "contains", "confidence": "EXTRACTED", "source_file": "C:\\Users\\Salivs\\Data\\laragon\\www\\drent-vibe\\backend\\vendor\\phpunit\\php-code-coverage\\ChangeLog-12.5.md", "source_location": "L13", "weight": 1.0}, {"source": "php_code_coverage_changelog_12_5_changelog", "target": "php_code_coverage_changelog_12_5_12_5_4_2026_04_12", "relation": "contains", "confidence": "EXTRACTED", "source_file": "C:\\Users\\Salivs\\Data\\laragon\\www\\drent-vibe\\backend\\vendor\\phpunit\\php-code-coverage\\ChangeLog-12.5.md", "source_location": "L17", "weight": 1.0}, {"source": "php_code_coverage_changelog_12_5_12_5_4_2026_04_12", "target": "php_code_coverage_changelog_12_5_fixed_19", "relation": "contains", "confidence": "EXTRACTED", "source_file": "C:\\Users\\Salivs\\Data\\laragon\\www\\drent-vibe\\backend\\vendor\\phpunit\\php-code-coverage\\ChangeLog-12.5.md", "source_location": "L19", "weight": 1.0}, {"source": "php_code_coverage_changelog_12_5_changelog", "target": "php_code_coverage_changelog_12_5_12_5_3_2026_02_06", "relation": "contains", "confidence": "EXTRACTED", "source_file": "C:\\Users\\Salivs\\Data\\laragon\\www\\drent-vibe\\backend\\vendor\\phpunit\\php-code-coverage\\ChangeLog-12.5.md", "source_location": "L23", "weight": 1.0}, {"source": "php_code_coverage_changelog_12_5_12_5_3_2026_02_06", "target": "php_code_coverage_changelog_12_5_fixed_25", "relation": "contains", "confidence": "EXTRACTED", "source_file": "C:\\Users\\Salivs\\Data\\laragon\\www\\drent-vibe\\backend\\vendor\\phpunit\\php-code-coverage\\ChangeLog-12.5.md", "source_location": "L25", "weight": 1.0}, {"source": "php_code_coverage_changelog_12_5_changelog", "target": "php_code_coverage_changelog_12_5_12_5_2_2025_12_24", "relation": "contains", "confidence": "EXTRACTED", "source_file": "C:\\Users\\Salivs\\Data\\laragon\\www\\drent-vibe\\backend\\vendor\\phpunit\\php-code-coverage\\ChangeLog-12.5.md", "source_location": "L29", "weight": 1.0}, {"source": "php_code_coverage_changelog_12_5_12_5_2_2025_12_24", "target": "php_code_coverage_changelog_12_5_fixed_31", "relation": "contains", "confidence": "EXTRACTED", "source_file": "C:\\Users\\Salivs\\Data\\laragon\\www\\drent-vibe\\backend\\vendor\\phpunit\\php-code-coverage\\ChangeLog-12.5.md", "source_location": "L31", "weight": 1.0}, {"source": "php_code_coverage_changelog_12_5_changelog", "target": "php_code_coverage_changelog_12_5_12_5_1_2025_12_08", "relation": "contains", "confidence": "EXTRACTED", "source_file": "C:\\Users\\Salivs\\Data\\laragon\\www\\drent-vibe\\backend\\vendor\\phpunit\\php-code-coverage\\ChangeLog-12.5.md", "source_location": "L35", "weight": 1.0}, {"source": "php_code_coverage_changelog_12_5_12_5_1_2025_12_08", "target": "php_code_coverage_changelog_12_5_changed", "relation": "contains", "confidence": "EXTRACTED", "source_file": "C:\\Users\\Salivs\\Data\\laragon\\www\\drent-vibe\\backend\\vendor\\phpunit\\php-code-coverage\\ChangeLog-12.5.md", "source_location": "L37", "weight": 1.0}, {"source": "php_code_coverage_changelog_12_5_changelog", "target": "php_code_coverage_changelog_12_5_12_5_0_2025_11_29", "relation": "contains", "confidence": "EXTRACTED", "source_file": "C:\\Users\\Salivs\\Data\\laragon\\www\\drent-vibe\\backend\\vendor\\phpunit\\php-code-coverage\\ChangeLog-12.5.md", "source_location": "L41", "weight": 1.0}, {"source": "php_code_coverage_changelog_12_5_12_5_0_2025_11_29", "target": "php_code_coverage_changelog_12_5_added", "relation": "contains", "confidence": "EXTRACTED", "source_file": "C:\\Users\\Salivs\\Data\\laragon\\www\\drent-vibe\\backend\\vendor\\phpunit\\php-code-coverage\\ChangeLog-12.5.md", "source_location": "L43", "weight": 1.0}, {"source": "php_code_coverage_changelog_12_5_12_5_0_2025_11_29", "target": "php_code_coverage_changelog_12_5_changed_47", "relation": "contains", "confidence": "EXTRACTED", "source_file": "C:\\Users\\Salivs\\Data\\laragon\\www\\drent-vibe\\backend\\vendor\\phpunit\\php-code-coverage\\ChangeLog-12.5.md", "source_location": "L47", "weight": 1.0}], "input_tokens": 0, "output_tokens": 0}