{"nodes": [{"id": "c_users_salivs_data_laragon_www_drent_vibe_backend_app_services_memberservice_php", "label": "MemberService.php", "file_type": "code", "source_file": "C:\\Users\\Salivs\\Data\\laragon\\www\\drent-vibe\\backend\\app\\Services\\MemberService.php", "source_location": "L1"}, {"id": "services_memberservice_memberservice", "label": "MemberService", "file_type": "code", "source_file": "C:\\Users\\Salivs\\Data\\laragon\\www\\drent-vibe\\backend\\app\\Services\\MemberService.php", "source_location": "L10"}, {"id": "services_memberservice_memberservice_list", "label": ".list()", "file_type": "code", "source_file": "C:\\Users\\Salivs\\Data\\laragon\\www\\drent-vibe\\backend\\app\\Services\\MemberService.php", "source_location": "L12"}, {"id": "services_memberservice_memberservice_createmember", "label": ".createMember()", "file_type": "code", "source_file": "C:\\Users\\Salivs\\Data\\laragon\\www\\drent-vibe\\backend\\app\\Services\\MemberService.php", "source_location": "L27"}, {"id": "services_memberservice_memberservice_updatemember", "label": ".updateMember()", "file_type": "code", "source_file": "C:\\Users\\Salivs\\Data\\laragon\\www\\drent-vibe\\backend\\app\\Services\\MemberService.php", "source_location": "L38"}, {"id": "services_memberservice_memberservice_activatemember", "label": ".activateMember()", "file_type": "code", "source_file": "C:\\Users\\Salivs\\Data\\laragon\\www\\drent-vibe\\backend\\app\\Services\\MemberService.php", "source_location": "L49"}, {"id": "services_memberservice_memberservice_updatestatus", "label": ".updateStatus()", "file_type": "code", "source_file": "C:\\Users\\Salivs\\Data\\laragon\\www\\drent-vibe\\backend\\app\\Services\\MemberService.php", "source_location": "L67"}, {"id": "services_memberservice_memberservice_extendmember", "label": ".extendMember()", "file_type": "code", "source_file": "C:\\Users\\Salivs\\Data\\laragon\\www\\drent-vibe\\backend\\app\\Services\\MemberService.php", "source_location": "L90"}, {"id": "services_memberservice_memberservice_getextensions", "label": ".getExtensions()", "file_type": "code", "source_file": "C:\\Users\\Salivs\\Data\\laragon\\www\\drent-vibe\\backend\\app\\Services\\MemberService.php", "source_location": "L117"}, {"id": "services_memberservice_memberservice_synccustomermembershipstatus", "label": ".syncCustomerMembershipStatus()", "file_type": "code", "source_file": "C:\\Users\\Salivs\\Data\\laragon\\www\\drent-vibe\\backend\\app\\Services\\MemberService.php", "source_location": "L122"}, {"id": "services_memberservice_memberservice_handlefileuploads", "label": ".handleFileUploads()", "file_type": "code", "source_file": "C:\\Users\\Salivs\\Data\\laragon\\www\\drent-vibe\\backend\\app\\Services\\MemberService.php", "source_location": "L143"}, {"id": "services_memberservice_memberservice_getdocumentpath", "label": ".getDocumentPath()", "file_type": "code", "source_file": "C:\\Users\\Salivs\\Data\\laragon\\www\\drent-vibe\\backend\\app\\Services\\MemberService.php", "source_location": "L178"}], "edges": [{"source": "c_users_salivs_data_laragon_www_drent_vibe_backend_app_services_memberservice_php", "target": "member", "relation": "imports", "context": "import", "confidence": "EXTRACTED", "source_file": "C:\\Users\\Salivs\\Data\\laragon\\www\\drent-vibe\\backend\\app\\Services\\MemberService.php", "source_location": "L5", "weight": 1.0}, {"source": "c_users_salivs_data_laragon_www_drent_vibe_backend_app_services_memberservice_php", "target": "db", "relation": "imports", "context": "import", "confidence": "EXTRACTED", "source_file": "C:\\Users\\Salivs\\Data\\laragon\\www\\drent-vibe\\backend\\app\\Services\\MemberService.php", "source_location": "L6", "weight": 1.0}, {"source": "c_users_salivs_data_laragon_www_drent_vibe_backend_app_services_memberservice_php", "target": "storage", "relation": "imports", "context": "import", "confidence": "EXTRACTED", "source_file": "C:\\Users\\Salivs\\Data\\laragon\\www\\drent-vibe\\backend\\app\\Services\\MemberService.php", "source_location": "L7", "weight": 1.0}, {"source": "c_users_salivs_data_laragon_www_drent_vibe_backend_app_services_memberservice_php", "target": "str", "relation": "imports", "context": "import", "confidence": "EXTRACTED", "source_file": "C:\\Users\\Salivs\\Data\\laragon\\www\\drent-vibe\\backend\\app\\Services\\MemberService.php", "source_location": "L8", "weight": 1.0}, {"source": "c_users_salivs_data_laragon_www_drent_vibe_backend_app_services_memberservice_php", "target": "services_memberservice_memberservice", "relation": "contains", "confidence": "EXTRACTED", "source_file": "C:\\Users\\Salivs\\Data\\laragon\\www\\drent-vibe\\backend\\app\\Services\\MemberService.php", "source_location": "L10", "weight": 1.0}, {"source": "services_memberservice_memberservice", "target": "services_memberservice_memberservice_list", "relation": "method", "confidence": "EXTRACTED", "source_file": "C:\\Users\\Salivs\\Data\\laragon\\www\\drent-vibe\\backend\\app\\Services\\MemberService.php", "source_location": "L12", "weight": 1.0}, {"source": "services_memberservice_memberservice", "target": "services_memberservice_memberservice_createmember", "relation": "method", "confidence": "EXTRACTED", "source_file": "C:\\Users\\Salivs\\Data\\laragon\\www\\drent-vibe\\backend\\app\\Services\\MemberService.php", "source_location": "L27", "weight": 1.0}, {"source": "services_memberservice_memberservice", "target": "services_memberservice_memberservice_updatemember", "relation": "method", "confidence": "EXTRACTED", "source_file": "C:\\Users\\Salivs\\Data\\laragon\\www\\drent-vibe\\backend\\app\\Services\\MemberService.php", "source_location": "L38", "weight": 1.0}, {"source": "services_memberservice_memberservice", "target": "services_memberservice_memberservice_activatemember", "relation": "method", "confidence": "EXTRACTED", "source_file": "C:\\Users\\Salivs\\Data\\laragon\\www\\drent-vibe\\backend\\app\\Services\\MemberService.php", "source_location": "L49", "weight": 1.0}, {"source": "services_memberservice_memberservice", "target": "services_memberservice_memberservice_updatestatus", "relation": "method", "confidence": "EXTRACTED", "source_file": "C:\\Users\\Salivs\\Data\\laragon\\www\\drent-vibe\\backend\\app\\Services\\MemberService.php", "source_location": "L67", "weight": 1.0}, {"source": "services_memberservice_memberservice", "target": "services_memberservice_memberservice_extendmember", "relation": "method", "confidence": "EXTRACTED", "source_file": "C:\\Users\\Salivs\\Data\\laragon\\www\\drent-vibe\\backend\\app\\Services\\MemberService.php", "source_location": "L90", "weight": 1.0}, {"source": "services_memberservice_memberservice", "target": "services_memberservice_memberservice_getextensions", "relation": "method", "confidence": "EXTRACTED", "source_file": "C:\\Users\\Salivs\\Data\\laragon\\www\\drent-vibe\\backend\\app\\Services\\MemberService.php", "source_location": "L117", "weight": 1.0}, {"source": "services_memberservice_memberservice", "target": "services_memberservice_memberservice_synccustomermembershipstatus", "relation": "method", "confidence": "EXTRACTED", "source_file": "C:\\Users\\Salivs\\Data\\laragon\\www\\drent-vibe\\backend\\app\\Services\\MemberService.php", "source_location": "L122", "weight": 1.0}, {"source": "services_memberservice_memberservice", "target": "services_memberservice_memberservice_handlefileuploads", "relation": "method", "confidence": "EXTRACTED", "source_file": "C:\\Users\\Salivs\\Data\\laragon\\www\\drent-vibe\\backend\\app\\Services\\MemberService.php", "source_location": "L143", "weight": 1.0}, {"source": "services_memberservice_memberservice", "target": "services_memberservice_memberservice_getdocumentpath", "relation": "method", "confidence": "EXTRACTED", "source_file": "C:\\Users\\Salivs\\Data\\laragon\\www\\drent-vibe\\backend\\app\\Services\\MemberService.php", "source_location": "L178", "weight": 1.0}, {"source": "services_memberservice_memberservice_createmember", "target": "services_memberservice_memberservice_handlefileuploads", "relation": "calls", "context": "call", "confidence": "EXTRACTED", "source_file": "C:\\Users\\Salivs\\Data\\laragon\\www\\drent-vibe\\backend\\app\\Services\\MemberService.php", "source_location": "L30", "weight": 1.0}, {"source": "services_memberservice_memberservice_createmember", "target": "services_memberservice_memberservice_synccustomermembershipstatus", "relation": "calls", "context": "call", "confidence": "EXTRACTED", "source_file": "C:\\Users\\Salivs\\Data\\laragon\\www\\drent-vibe\\backend\\app\\Services\\MemberService.php", "source_location": "L32", "weight": 1.0}, {"source": "services_memberservice_memberservice_updatemember", "target": "services_memberservice_memberservice_handlefileuploads", "relation": "calls", "context": "call", "confidence": "EXTRACTED", "source_file": "C:\\Users\\Salivs\\Data\\laragon\\www\\drent-vibe\\backend\\app\\Services\\MemberService.php", "source_location": "L41", "weight": 1.0}, {"source": "services_memberservice_memberservice_updatemember", "target": "services_memberservice_memberservice_synccustomermembershipstatus", "relation": "calls", "context": "call", "confidence": "EXTRACTED", "source_file": "C:\\Users\\Salivs\\Data\\laragon\\www\\drent-vibe\\backend\\app\\Services\\MemberService.php", "source_location": "L43", "weight": 1.0}, {"source": "services_memberservice_memberservice_activatemember", "target": "services_memberservice_memberservice_synccustomermembershipstatus", "relation": "calls", "context": "call", "confidence": "EXTRACTED", "source_file": "C:\\Users\\Salivs\\Data\\laragon\\www\\drent-vibe\\backend\\app\\Services\\MemberService.php", "source_location": "L61", "weight": 1.0}, {"source": "services_memberservice_memberservice_updatestatus", "target": "services_memberservice_memberservice_synccustomermembershipstatus", "relation": "calls", "context": "call", "confidence": "EXTRACTED", "source_file": "C:\\Users\\Salivs\\Data\\laragon\\www\\drent-vibe\\backend\\app\\Services\\MemberService.php", "source_location": "L84", "weight": 1.0}, {"source": "services_memberservice_memberservice_extendmember", "target": "services_memberservice_memberservice_synccustomermembershipstatus", "relation": "calls", "context": "call", "confidence": "EXTRACTED", "source_file": "C:\\Users\\Salivs\\Data\\laragon\\www\\drent-vibe\\backend\\app\\Services\\MemberService.php", "source_location": "L111", "weight": 1.0}], "raw_calls": [{"caller_nid": "services_memberservice_memberservice_list", "callee": "Member", "is_member_call": false, "source_file": "C:\\Users\\Salivs\\Data\\laragon\\www\\drent-vibe\\backend\\app\\Services\\MemberService.php", "source_location": "L14"}, {"caller_nid": "services_memberservice_memberservice_list", "callee": "isset", "is_member_call": false, "source_file": "C:\\Users\\Salivs\\Data\\laragon\\www\\drent-vibe\\backend\\app\\Services\\MemberService.php", "source_location": "L16"}, {"caller_nid": "services_memberservice_memberservice_list", "callee": "where", "is_member_call": true, "source_file": "C:\\Users\\Salivs\\Data\\laragon\\www\\drent-vibe\\backend\\app\\Services\\MemberService.php", "source_location": "L17"}, {"caller_nid": "services_memberservice_memberservice_list", "callee": "isset", "is_member_call": false, "source_file": "C:\\Users\\Salivs\\Data\\laragon\\www\\drent-vibe\\backend\\app\\Services\\MemberService.php", "source_location": "L20"}, {"caller_nid": "services_memberservice_memberservice_list", "callee": "where", "is_member_call": true, "source_file": "C:\\Users\\Salivs\\Data\\laragon\\www\\drent-vibe\\backend\\app\\Services\\MemberService.php", "source_location": "L21"}, {"caller_nid": "services_memberservice_memberservice_list", "callee": "paginate", "is_member_call": true, "source_file": "C:\\Users\\Salivs\\Data\\laragon\\www\\drent-vibe\\backend\\app\\Services\\MemberService.php", "source_location": "L24"}, {"caller_nid": "services_memberservice_memberservice_list", "callee": "latest", "is_member_call": true, "source_file": "C:\\Users\\Salivs\\Data\\laragon\\www\\drent-vibe\\backend\\app\\Services\\MemberService.php", "source_location": "L24"}, {"caller_nid": "services_memberservice_memberservice_createmember", "callee": "DB", "is_member_call": false, "source_file": "C:\\Users\\Salivs\\Data\\laragon\\www\\drent-vibe\\backend\\app\\Services\\MemberService.php", "source_location": "L29"}, {"caller_nid": "services_memberservice_memberservice_createmember", "callee": "Member", "is_member_call": false, "source_file": "C:\\Users\\Salivs\\Data\\laragon\\www\\drent-vibe\\backend\\app\\Services\\MemberService.php", "source_location": "L31"}, {"caller_nid": "services_memberservice_memberservice_updatemember", "callee": "DB", "is_member_call": false, "source_file": "C:\\Users\\Salivs\\Data\\laragon\\www\\drent-vibe\\backend\\app\\Services\\MemberService.php", "source_location": "L40"}, {"caller_nid": "services_memberservice_memberservice_updatemember", "callee": "update", "is_member_call": true, "source_file": "C:\\Users\\Salivs\\Data\\laragon\\www\\drent-vibe\\backend\\app\\Services\\MemberService.php", "source_location": "L42"}, {"caller_nid": "services_memberservice_memberservice_updatemember", "callee": "refresh", "is_member_call": true, "source_file": "C:\\Users\\Salivs\\Data\\laragon\\www\\drent-vibe\\backend\\app\\Services\\MemberService.php", "source_location": "L43"}, {"caller_nid": "services_memberservice_memberservice_activatemember", "callee": "DB", "is_member_call": false, "source_file": "C:\\Users\\Salivs\\Data\\laragon\\www\\drent-vibe\\backend\\app\\Services\\MemberService.php", "source_location": "L51"}, {"caller_nid": "services_memberservice_memberservice_activatemember", "callee": "date", "is_member_call": false, "source_file": "C:\\Users\\Salivs\\Data\\laragon\\www\\drent-vibe\\backend\\app\\Services\\MemberService.php", "source_location": "L53"}, {"caller_nid": "services_memberservice_memberservice_activatemember", "callee": "strtoupper", "is_member_call": false, "source_file": "C:\\Users\\Salivs\\Data\\laragon\\www\\drent-vibe\\backend\\app\\Services\\MemberService.php", "source_location": "L53"}, {"caller_nid": "services_memberservice_memberservice_activatemember", "callee": "Str", "is_member_call": false, "source_file": "C:\\Users\\Salivs\\Data\\laragon\\www\\drent-vibe\\backend\\app\\Services\\MemberService.php", "source_location": "L53"}, {"caller_nid": "services_memberservice_memberservice_activatemember", "callee": "now", "is_member_call": false, "source_file": "C:\\Users\\Salivs\\Data\\laragon\\www\\drent-vibe\\backend\\app\\Services\\MemberService.php", "source_location": "L57"}, {"caller_nid": "services_memberservice_memberservice_activatemember", "callee": "addYear", "is_member_call": true, "source_file": "C:\\Users\\Salivs\\Data\\laragon\\www\\drent-vibe\\backend\\app\\Services\\MemberService.php", "source_location": "L58"}, {"caller_nid": "services_memberservice_memberservice_activatemember", "callee": "now", "is_member_call": false, "source_file": "C:\\Users\\Salivs\\Data\\laragon\\www\\drent-vibe\\backend\\app\\Services\\MemberService.php", "source_location": "L58"}, {"caller_nid": "services_memberservice_memberservice_activatemember", "callee": "save", "is_member_call": true, "source_file": "C:\\Users\\Salivs\\Data\\laragon\\www\\drent-vibe\\backend\\app\\Services\\MemberService.php", "source_location": "L59"}, {"caller_nid": "services_memberservice_memberservice_activatemember", "callee": "refresh", "is_member_call": true, "source_file": "C:\\Users\\Salivs\\Data\\laragon\\www\\drent-vibe\\backend\\app\\Services\\MemberService.php", "source_location": "L61"}, {"caller_nid": "services_memberservice_memberservice_updatestatus", "callee": "DB", "is_member_call": false, "source_file": "C:\\Users\\Salivs\\Data\\laragon\\www\\drent-vibe\\backend\\app\\Services\\MemberService.php", "source_location": "L69"}, {"caller_nid": "services_memberservice_memberservice_updatestatus", "callee": "date", "is_member_call": false, "source_file": "C:\\Users\\Salivs\\Data\\laragon\\www\\drent-vibe\\backend\\app\\Services\\MemberService.php", "source_location": "L73"}, {"caller_nid": "services_memberservice_memberservice_updatestatus", "callee": "strtoupper", "is_member_call": false, "source_file": "C:\\Users\\Salivs\\Data\\laragon\\www\\drent-vibe\\backend\\app\\Services\\MemberService.php", "source_location": "L73"}, {"caller_nid": "services_memberservice_memberservice_updatestatus", "callee": "Str", "is_member_call": false, "source_file": "C:\\Users\\Salivs\\Data\\laragon\\www\\drent-vibe\\backend\\app\\Services\\MemberService.php", "source_location": "L73"}, {"caller_nid": "services_memberservice_memberservice_updatestatus", "callee": "now", "is_member_call": false, "source_file": "C:\\Users\\Salivs\\Data\\laragon\\www\\drent-vibe\\backend\\app\\Services\\MemberService.php", "source_location": "L76"}, {"caller_nid": "services_memberservice_memberservice_updatestatus", "callee": "addYear", "is_member_call": true, "source_file": "C:\\Users\\Salivs\\Data\\laragon\\www\\drent-vibe\\backend\\app\\Services\\MemberService.php", "source_location": "L79"}, {"caller_nid": "services_memberservice_memberservice_updatestatus", "callee": "now", "is_member_call": false, "source_file": "C:\\Users\\Salivs\\Data\\laragon\\www\\drent-vibe\\backend\\app\\Services\\MemberService.php", "source_location": "L79"}, {"caller_nid": "services_memberservice_memberservice_updatestatus", "callee": "save", "is_member_call": true, "source_file": "C:\\Users\\Salivs\\Data\\laragon\\www\\drent-vibe\\backend\\app\\Services\\MemberService.php", "source_location": "L82"}, {"caller_nid": "services_memberservice_memberservice_updatestatus", "callee": "refresh", "is_member_call": true, "source_file": "C:\\Users\\Salivs\\Data\\laragon\\www\\drent-vibe\\backend\\app\\Services\\MemberService.php", "source_location": "L84"}, {"caller_nid": "services_memberservice_memberservice_extendmember", "callee": "DB", "is_member_call": false, "source_file": "C:\\Users\\Salivs\\Data\\laragon\\www\\drent-vibe\\backend\\app\\Services\\MemberService.php", "source_location": "L92"}, {"caller_nid": "services_memberservice_memberservice_extendmember", "callee": "create", "is_member_call": true, "source_file": "C:\\Users\\Salivs\\Data\\laragon\\www\\drent-vibe\\backend\\app\\Services\\MemberService.php", "source_location": "L96"}, {"caller_nid": "services_memberservice_memberservice_extendmember", "callee": "extensions", "is_member_call": true, "source_file": "C:\\Users\\Salivs\\Data\\laragon\\www\\drent-vibe\\backend\\app\\Services\\MemberService.php", "source_location": "L96"}, {"caller_nid": "services_memberservice_memberservice_extendmember", "callee": "id", "is_member_call": true, "source_file": "C:\\Users\\Salivs\\Data\\laragon\\www\\drent-vibe\\backend\\app\\Services\\MemberService.php", "source_location": "L100"}, {"caller_nid": "services_memberservice_memberservice_extendmember", "callee": "auth", "is_member_call": false, "source_file": "C:\\Users\\Salivs\\Data\\laragon\\www\\drent-vibe\\backend\\app\\Services\\MemberService.php", "source_location": "L100"}, {"caller_nid": "services_memberservice_memberservice_extendmember", "callee": "save", "is_member_call": true, "source_file": "C:\\Users\\Salivs\\Data\\laragon\\www\\drent-vibe\\backend\\app\\Services\\MemberService.php", "source_location": "L109"}, {"caller_nid": "services_memberservice_memberservice_extendmember", "callee": "refresh", "is_member_call": true, "source_file": "C:\\Users\\Salivs\\Data\\laragon\\www\\drent-vibe\\backend\\app\\Services\\MemberService.php", "source_location": "L111"}, {"caller_nid": "services_memberservice_memberservice_getextensions", "callee": "get", "is_member_call": true, "source_file": "C:\\Users\\Salivs\\Data\\laragon\\www\\drent-vibe\\backend\\app\\Services\\MemberService.php", "source_location": "L119"}, {"caller_nid": "services_memberservice_memberservice_getextensions", "callee": "with", "is_member_call": true, "source_file": "C:\\Users\\Salivs\\Data\\laragon\\www\\drent-vibe\\backend\\app\\Services\\MemberService.php", "source_location": "L119"}, {"caller_nid": "services_memberservice_memberservice_getextensions", "callee": "extensions", "is_member_call": true, "source_file": "C:\\Users\\Salivs\\Data\\laragon\\www\\drent-vibe\\backend\\app\\Services\\MemberService.php", "source_location": "L119"}, {"caller_nid": "services_memberservice_memberservice_synccustomermembershipstatus", "callee": "loadMissing", "is_member_call": true, "source_file": "C:\\Users\\Salivs\\Data\\laragon\\www\\drent-vibe\\backend\\app\\Services\\MemberService.php", "source_location": "L124"}, {"caller_nid": "services_memberservice_memberservice_synccustomermembershipstatus", "callee": "in_array", "is_member_call": false, "source_file": "C:\\Users\\Salivs\\Data\\laragon\\www\\drent-vibe\\backend\\app\\Services\\MemberService.php", "source_location": "L133"}, {"caller_nid": "services_memberservice_memberservice_synccustomermembershipstatus", "callee": "save", "is_member_call": true, "source_file": "C:\\Users\\Salivs\\Data\\laragon\\www\\drent-vibe\\backend\\app\\Services\\MemberService.php", "source_location": "L140"}, {"caller_nid": "services_memberservice_memberservice_synccustomermembershipstatus", "callee": "forceFill", "is_member_call": true, "source_file": "C:\\Users\\Salivs\\Data\\laragon\\www\\drent-vibe\\backend\\app\\Services\\MemberService.php", "source_location": "L140"}, {"caller_nid": "services_memberservice_memberservice_handlefileuploads", "callee": "isset", "is_member_call": false, "source_file": "C:\\Users\\Salivs\\Data\\laragon\\www\\drent-vibe\\backend\\app\\Services\\MemberService.php", "source_location": "L150"}, {"caller_nid": "services_memberservice_memberservice_handlefileuploads", "callee": "delete", "is_member_call": true, "source_file": "C:\\Users\\Salivs\\Data\\laragon\\www\\drent-vibe\\backend\\app\\Services\\MemberService.php", "source_location": "L152"}, {"caller_nid": "services_memberservice_memberservice_handlefileuploads", "callee": "Storage", "is_member_call": false, "source_file": "C:\\Users\\Salivs\\Data\\laragon\\www\\drent-vibe\\backend\\app\\Services\\MemberService.php", "source_location": "L152"}, {"caller_nid": "services_memberservice_memberservice_handlefileuploads", "callee": "store", "is_member_call": true, "source_file": "C:\\Users\\Salivs\\Data\\laragon\\www\\drent-vibe\\backend\\app\\Services\\MemberService.php", "source_location": "L154"}, {"caller_nid": "services_memberservice_memberservice_handlefileuploads", "callee": "isset", "is_member_call": false, "source_file": "C:\\Users\\Salivs\\Data\\laragon\\www\\drent-vibe\\backend\\app\\Services\\MemberService.php", "source_location": "L157"}, {"caller_nid": "services_memberservice_memberservice_handlefileuploads", "callee": "delete", "is_member_call": true, "source_file": "C:\\Users\\Salivs\\Data\\laragon\\www\\drent-vibe\\backend\\app\\Services\\MemberService.php", "source_location": "L159"}, {"caller_nid": "services_memberservice_memberservice_handlefileuploads", "callee": "Storage", "is_member_call": false, "source_file": "C:\\Users\\Salivs\\Data\\laragon\\www\\drent-vibe\\backend\\app\\Services\\MemberService.php", "source_location": "L159"}, {"caller_nid": "services_memberservice_memberservice_handlefileuploads", "callee": "store", "is_member_call": true, "source_file": "C:\\Users\\Salivs\\Data\\laragon\\www\\drent-vibe\\backend\\app\\Services\\MemberService.php", "source_location": "L161"}, {"caller_nid": "services_memberservice_memberservice_handlefileuploads", "callee": "isset", "is_member_call": false, "source_file": "C:\\Users\\Salivs\\Data\\laragon\\www\\drent-vibe\\backend\\app\\Services\\MemberService.php", "source_location": "L164"}, {"caller_nid": "services_memberservice_memberservice_handlefileuploads", "callee": "is_array", "is_member_call": false, "source_file": "C:\\Users\\Salivs\\Data\\laragon\\www\\drent-vibe\\backend\\app\\Services\\MemberService.php", "source_location": "L164"}, {"caller_nid": "services_memberservice_memberservice_handlefileuploads", "callee": "store", "is_member_call": true, "source_file": "C:\\Users\\Salivs\\Data\\laragon\\www\\drent-vibe\\backend\\app\\Services\\MemberService.php", "source_location": "L169"}, {"caller_nid": "services_memberservice_memberservice_handlefileuploads", "callee": "array_merge", "is_member_call": false, "source_file": "C:\\Users\\Salivs\\Data\\laragon\\www\\drent-vibe\\backend\\app\\Services\\MemberService.php", "source_location": "L172"}, {"caller_nid": "services_memberservice_memberservice_getdocumentpath", "callee": "str_starts_with", "is_member_call": false, "source_file": "C:\\Users\\Salivs\\Data\\laragon\\www\\drent-vibe\\backend\\app\\Services\\MemberService.php", "source_location": "L190"}, {"caller_nid": "services_memberservice_memberservice_getdocumentpath", "callee": "str_replace", "is_member_call": false, "source_file": "C:\\Users\\Salivs\\Data\\laragon\\www\\drent-vibe\\backend\\app\\Services\\MemberService.php", "source_location": "L191"}]}